{"nodes": [{"id": "seed_final_test", "label": "seed_final_test.py", "file_type": "code", "source_file": "seed_final_test.py", "source_location": "L1"}, {"id": "seed_final_test_seed_final_test", "label": "seed_final_test()", "file_type": "code", "source_file": "seed_final_test.py", "source_location": "L11"}], "edges": [{"source": "seed_final_test", "target": "json", "relation": "imports", "confidence": "EXTRACTED", "source_file": "seed_final_test.py", "source_location": "L1", "weight": 1.0}, {"source": "seed_final_test", "target": "os", "relation": "imports", "confidence": "EXTRACTED", "source_file": "seed_final_test.py", "source_location": "L2", "weight": 1.0}, {"source": "seed_final_test", "target": "django", "relation": "imports", "confidence": "EXTRACTED", "source_file": "seed_final_test.py", "source_location": "L3", "weight": 1.0}, {"source": "seed_final_test", "target": "learning_models", "relation": "imports_from", "confidence": "EXTRACTED", "source_file": "seed_final_test.py", "source_location": "L9", "weight": 1.0}, {"source": "seed_final_test", "target": "seed_final_test_seed_final_test", "relation": "contains", "confidence": "EXTRACTED", "source_file": "seed_final_test.py", "source_location": "L11", "weight": 1.0}]}